{"name":"すごいHaskell読書会 in 大阪","tagline":"平日夜に西梅田で開催されるH本読書会","body":"### この読書会について\r\n```\r\n訳あって Haskell を勉強したくなったのですごいH本の読書会をします。\r\n```\r\n\r\n[すごいHaskellたのしく学ぼう!](http://www.amazon.co.jp/dp/4274068854/) (原著：[Learn You a Haskell for Great Good!](http://learnyouahaskell.com/chapters) ) を課題図書とした読書会です。大阪・西梅田のビルで3-4週に1回程度のペースで開催しています。\r\n\r\n順番に指定された章について発表する輪講スタイルで開催しています。\r\n\r\n発表の後、参加者各自で考えてきた練習問題を解いて理解を深める時間もあります。\r\n\r\n開催中・開催前後のやりとりは[Lingrルーム](http://lingr.com/room/sugoih)やTwitterの #sugoih でやっています。\r\n\r\n### 今後の開催\r\n#### すごいHaskell読書会 in 大阪 #12 2013/08/19(Mon)\r\n第13章：モナドがいっぱい\r\n\r\n**参加受付中** ATND から参加登録： http://atnd.org/events/42677\r\n\r\n- 日時：2013/06/25(Thr) 19:15 - 21:30\r\n- 場所：フェンリル株式会社 大阪本社 (大阪府大阪市北区梅田 2-4-9 ブリーゼタワー 12F)\r\n- 発表 @yashigani\r\n\r\n***\r\n\r\n\r\n### これまでの開催\r\n#### すごいHaskell読書会 in 大阪 #11 2013/07/23(Tue)\r\n第12章：モノイド\r\n\r\n- 発表 @akanehara\r\n- 練習問題\r\n\t- https://gist.github.com/cojna/5857876\r\n\r\n#### すごいHaskell読書会 in 大阪 #10 2013/06/13(Thr)\r\n第11章：ファンクターからアプリカティブファンクターへ\r\n\r\n- 発表 @iseebi\r\n\t- http://www.slideshare.net/iseebi/haskell10\r\n- 練習問題\r\n\t- https://gist.github.com/cojna/5857876\r\n\r\n#### [すごいHaskell読書会 in 大阪 #9](http://atnd.org/events/38591) 2013/05/09(Thr)\r\n練習問題復習大会\r\n\r\n#### [すごいHaskell読書会 in 大阪 #8](http://atnd.org/events/38277) 2013/04/08(Mon)\r\n第9章：もっと入力、もっと出力(2) (9.3 ToDoリスト)\r\n\r\n- 発表 @cojna\r\n\t- https://gist.github.com/cojna/617d19bbb56ad9f3b1c8\r\n- 練習問題\r\n\t- https://gist.github.com/nushio3/5253230\r\n\t- https://gist.github.com/IKEGAMIDaisuke/5335869\r\n\r\n#### [すごいHaskell読書会 in 大阪 #7](http://atnd.org/events/37645) 2013/03/27(Wed)\r\n第8章：入出力 / 第9章：もっと入力、もっと出力(1) (9.2 ファイルの読み書きまで)\r\n\r\n- 発表 @yashigani\r\n\t- https://gist.github.com/yashigani/5231928\r\n- 練習問題\r\n\t- https://gist.github.com/yashigani/5231928#-12\r\n\r\n#### [すごいHaskell読書会 in 大阪 #6](http://atnd.org/events/36958) 2013/03/08(Fri)\r\n第7章：型や型クラスを自分で作ろう(2)」(7.7 再帰的なデータ構造から章末まで)\r\n\r\n- 発表 @cojna\r\n\t- http://www.slideshare.net/cojna/slide-17056272\r\n- 練習問題\r\n\t- https://gist.github.com/anonymous/5345920\r\n\r\n#### [すごいHaskell読書会 in 大阪 #5](http://atnd.org/events/36958) 2013/02/13(Wed)\r\n第7章：型や型クラスを自分で作ろう(1) (7.6 型シノニムまで)\r\n\r\n- 発表 @kakkun61\r\n\t- http://www.slideshare.net/kakkun61/haskell-in-5\r\n- 練習問題\r\n\t- https://gist.github.com/yashigani/4943873\r\n\r\n#### [すごいHaskell読書会 in 大阪 #4](http://atnd.org/events/36958) 2013/01/30(Wed)\r\n第6章：モジュール\r\n\r\n- 発表 @iseebi\r\n\t- http://www.slideshare.net/iseebi/haskell-in-4-6\r\n- 練習問題\r\n\t- https://github.com/nushio3/practice/blob/master/sugoiH-OSK/04/problem.md\r\n\t- https://gist.github.com/akanehara/4671481\r\n\r\n#### [すごいHaskell読書会 in 大阪 #3](http://atnd.org/events/36958) 2013/01/11(Fri)\r\n第5章：高階関数\r\n\r\n- 発表 @akanehara\r\n\t- http://akanehara.info/sugoih3/#/title\r\n- 練習問題\r\n\t- https://gist.github.com/akanehara/4509540\r\n\r\n#### [すごいHaskell読書会 in 大阪 #2](http://atnd.org/events/36958) 2012/11/30(Fri)\r\n第3章：関数の構文 / 第4章：Hello 再帰！\r\n\r\n- 発表 @koko_u\r\n\t- http://koko-u.github.com/haskell_book_reading/#1\r\n- 練習問題\r\n\t- https://gist.github.com/anonymous/5342835\r\n\r\n#### [すごいHaskell読書会 in 大阪 #1](http://atnd.org/events/36958) 2012/11/09(Fri)\r\n第1章：はじめの第一歩 / 第2章：型を信じろ！\r\n\r\n- 発表 @yashigani\r\n\t- http://www.slideshare.net/yashigani/haskell-in\r\n- 練習問題\r\n\t- https://gist.github.com/yashigani/5340466","google":"UA-348212-8","note":"Don't delete this file! It's used internally to help with page regeneration."}